{"subjects": [{"subjectName": "Data Structures And Algorithm", "units": [{"unitName": "Introduction", "topics": ["Data Structure", "Algorithm", "Importance of Algorithm Analysis", "Complexity of an Algorithm", "Asymptotic Analysis and Notations", "Big O Notation", "Big Omega Notation", "Big Theta Notation", "Rate of Growth and Big O Notation", "Array", "Memory Representation of One - Dimensional Array", "Memory Representation of Two - Dimensional Arrays", "Linked List", "Linked List", "One - way Linked List", "Traversal of Linked List", "Searching", "Memory Allocation and Deallocation", "Insertion in Linked List", "Deletion from Linked List", "Copying a List into Other List", "Merging Two Linked Lists", "Splitting a List into Two Lists", "Reversing One way linked List", "Circular Linked List", "Applications of Circular Linked List Sparse Arrays", "Implementing other Data Structures", "Complexity analysis of Link List"]}, {"unitName": "Stack & Queue & Tree", "topics": ["Stack", "Introduction", "Operations on the Stack Memory Representation of Stack", "Array Representation of Stack", "Applications of Stack", "Evaluation of Arithmetic Expression", "Matching Parenthesis", "infix and postfix operations", "Recursion", "Queue", "Introduction", "Queue", "Operations on the Queue", "Memory Representation of Queue", "Array representation of queue", "Linked List Representation of Queue", "Circular Queue", "Tree", "Tree", "Binary Tree", "Properties of Binary Tree", "Memory Representation of Binary Tree", "Operations Performed on Binary Tree", "Reconstruction of Binary Tree from its Traversals", "Binary Search Tree", "Operations on Binary Search Tree", "Heap Tree", "Operation on Heap", "Heap Sort"]}, {"unitName": "Graph & Hashing", "topics": ["Graph", "Introduction", "Graph", "Graph Terminology", "Memory Representation of Graph", "Adjacency Matrix Representation of Graph", "Adjacency List or Linked Representation of Graph", "Operations Performed on Graph", "Graph Traversal", "Applications of the Graph", "Hash function", "Address calculation techniques", "Common hashing functions Collision resolution", "Linear probing", "Quadratic", "Double hashing", "Buckethashing", "Deletion and rehashing", "Complexity comparison of different sorting algorithms"]}]}, {"subjectName": "Data structures And Algorithm LAB", "units": [{"unitName": "Module 1", "topics": ["Implement the following", "Write a program to store the elements in 1 - D array and perform the operations like searching, sorting and reversing the elements.", "Read the two arrays from the user and merge them and display the elements in sorted order.", "Write a program to perform the Matrix addition, Multiplication and Transpose Operation.", "Implement the following for Stack", "Write a program to convert an infix expression to postfix and prefix conversion.", "Implement the following for Queue", "Write a program to implement the concept of Queue with Insert, Delete, Display and Exit operations.", "Write a program to implement the concept of Circular Queue"]}, {"unitName": "Module 2", "topics": ["Implement the following for Linked List", "Write a program to create a single linked list and display the node elements in reverse order.", "Write a program to search the elements in the linked list and display the same", "Write a program to create double linked list and sort the elements in the linked list"]}, {"unitName": "Module 3", "topics": ["Implement the sorting techniques", "Write a program to implement selection sort.", "Write a program to implement insertion sort.", "Implement Binary Search"]}]}, {"subjectName": "Software Engineering", "units": [{"unitName": "Module 1", "topics": ["The Nature of Software", "Defining Software", "Software Application Domains", "Legacy Software", "The Changing Nature of Software", "Software Engineering", "Defining the Discipline", "The Software Process", "The Process Framework", "Umbrella Activities", "Process Adaptation", "Software Engineering Practice", "The Essence of Practice", "General Principles", "Process Models", "Prescriptive Process Models", "The Waterfall Model", "Incremental Process Models", "Evolutionary Process Models", "Concurrent Models", "Specialized Process Models", "Component - Based Development", "The Formal Methods Model", "Aspect - Oriented Software Development", "The Unified Process", "Phases of the Unified Process", "Personal and Team Process Models", "Personal Software Process", "Team Software Process", "Process Technology", "Product and Process"]}, {"unitName": "Module 2", "topics": ["Agile Development", "What Is Agility?", "Agility and the Cost of Change", "What Is an Agile Process?", "Agility Principles", "The Politics of Agile Development", "Extreme Programming", "Other Agile Process Models", "Scrum", "Dynamic Systems Development Method", "Agile Modeling", "Agile Unified Process", "A Tool Set for the Agile Process", "Understanding Requirements", "Requirements Engineering", "Establishing the Groundwork", "Eliciting Requirements", "Developing Use Cases", "Building the Analysis Model", "Negotiating Requirements", "Requirements Monitoring", "Validating Requirements", "Avoiding Common Mistakes", "Introduction to UML", "Class Diagram", "Deployment Diagram", "Use Case Diagram", "Sequence Diagram", "Communication Diagram", "Activity Diagram", "State Diagram"]}, {"unitName": "Module 3", "topics": ["Design Concepts", "Design within the Context of Software Engineering", "The Design Process", "Software Quality Guidelines and Attributes", "The Evolution of Software Design", "Design Concepts", "Abstraction", "Architecture", "Patterns", "Separation of Concerns", "Modularity", "Information Hiding", "Functional Independence", "Refinement", "Aspects", "Refactoring", "Object - Oriented Design Concepts", "Design Classes", "Dependency Inversion", "Design for Test", "The Design Model", "Data Design Elements", "Architectural Design Elements", "Interface Design Elements", "Component - Level Design Elements", "Deployment - Level Design Elements", "Software testing", "A Strategic Approach to Software Testing", "Strategic Issues", "Unit Testing", "Integration Testing", "Validation Testing", "Validation - Test Criteria", "Configuration Review", "Alpha and Beta Testing", "System Testing", "Recovery Testing", "Security Testing", "Stress Testing", "Performance Testing", "Deployment Testing"]}]}, {"subjectName": "Python Programming LAB", "units": [{"unitName": "Module 1", "topics": ["Introduction and Use of Software and Basic Programs to implement conditional statements, looping and control statements"]}, {"unitName": "Module 2", "topics": ["Programs to implement the concept of functions and strings"]}, {"unitName": "Module 3", "topics": ["Programs to implement the concept of Lists, Tuples and Dictionaries"]}]}, {"subjectName": "Networking Technology", "units": [{"unitName": "Module 1", "topics": ["Introduction", "Data and Information", "Characteristics of Data Communication", "Components of data communication", "Data representation", "Data flow", "Simplex", "Full Duplex", "Half Duplex", "Physical structure", "point to point and multipoint", "Physical topology", "Bus", "Star", "Mesh", "Ring and Hybrid", "Categories of network", "LAN", "WAN and MAN", "protocols and standard", "Standards in networking", "De facto and Dejure standard", "Standard organization", "Network Models", "OSI model", "Layers in OSI Model", "TCP/IP model", "Addressing in TCP/IP", "Types of transmission mode", "serial and parallel transmission", "Introduction to Physical layer", "Introduction to Multiplexing", "Time division multiplexing", "Synchronous and Asynchronous medium", "Transmission Media", "Guided and unguided media", "Guided Media", "Twisted pair", "coaxial and fibre optic cable", "Unguided media", "wireless", "Radio Waves", "Microwaves", "Infrared", "Introduction to NIC card", "Comparison between switch and hub", "Bridge", "Router", "Gateway"]}, {"unitName": "Module 2", "topics": ["Introduction to Data link layer and Network layer", "Data link layer", "Types of error", "Detection vs correction", "CRC", "Introduction to Network layer", "Introduction to switching", "packet switching in detail", "IPV4 addresses", "classful and classless addressing", "NAT", "Internet protocol version 4 datagram frame format", "fragmentation", "checksum", "IPv6 frame format", "IPV 6 address", "ARP \u2013 address mapping", "packet format", "RIP", "OSPF and BGP", "Intra and interdomain routing", "distance vector routing algorithm", "RIP introduction", "Timers in RIP", "Link state routing", "OSPF", "Areas", "Dijkstra\u2019s algorithm", "metrics", "types of links", "OSPF packets", "BGP", "path vector routing", "Types of BGP packets"]}, {"unitName": "Module 3", "topics": ["Transport and application layer", "Transport layer features and services", "TCP packet", "UDP packet", "UDP features", "error control", "TCP numbering system", "TCP connection", "three - way handshaking", "data transfer", "connection termination", "Error control in TCP", "Application layer", "SMTP", "DHCP", "FTP"]}]}, {"subjectName": "Networking Technology LAB", "units": [{"unitName": "List of Practical", "topics": ["IPv4 Addressing and Subnetting", "Use of ping and tracert / traceroute, ipconfig / ifconfig, route and arp utilities.", "Configure IP static routing.", "Configure IP routing using RIP.", "Configuring Simple OSPF.", "Configuring DHCP server and client.", "Create virtual PC based network using virtualization software and virtual NIC.", "Configuring DNS Server and client.", "Configuring OSPF with multiple areas.", "Use of Wireshark to scan and check the packet information of following protocols HTTP, ICMP, TCP, SMTP, POP3"]}]}, {"subjectName": "Management Information System", "units": [{"unitName": "Module 1", "topics": ["Information Systems in Global Business Today", "The role of Information system in Business", "perspectives on Information system", "contemporary approaches to Information Systems.", "Global E - business and Collaboration", "Business processes and information systems", "types of Information Systems", "Information Technology Infrastructure", "IT Infrastructure", "Technology drivers of Infrastructure Evolution", "Contemporary Hardware platform", "Contemporary software platform trends", "management issues"]}, {"unitName": "Module 2", "topics": ["Achieving Operational Excellence and Customer Intimacy", "Enterprise Applications", "What is enterprise system", "Supply chain management system", "customer relational management systems", "Enterprise applications new opportunities and challenges", "Managing Knowledge", "The knowledge management landscape", "Enterprise wise knowledge management", "knowledge work system", "intelligent techniques", "Ethical and Social Issues in Information Systems", "Understanding ethical and Social Issues related to systems", "ethics in Information Society", "Intellectual Property", "System Quality", "data quality and system errors"]}]}, {"subjectName": "Multimedia and Animation I", "units": [{"unitName": "Fundamentals of Visual Design", "topics": ["Understanding design principles (balance, contrast, alignment, repetition, proximity).", "Working with visual elements (lines, shapes, forms, textures, and white space).", "Basics of colour theory and its application in design.", "Role of typography in composition and branding.", "Fundamentals of layout and composition techniques."]}, {"unitName": "Image Editing and Composition Using Adobe Photoshop", "topics": ["Introduction to Adobe Photoshop: Interface and essential tools.", "Working with layers, masks, and blending modes for creative composition.", "Applying adjustments (brightness, contrast, hue/saturation) for image enhancement.", "Selection tools and retouching techniques for seamless editing.", "Exporting images for different formats (web, print, and social media)."]}, {"unitName": "Basics of Animation & Motion Graphics", "topics": ["Introduction to animation principles (timing, easing, and motion).", "Understanding keyframes and timeline - based animation in Photoshop/After Effects.", "Creating simple motion effects (opacity, scaling, rotation).", "Designing text animations and transitions.", "Exporting animated content (GIFs, MP4, and other media formats)."]}]}, {"subjectName": "Linear Algebra Concepts", "units": [{"unitName": "Module 1", "topics": ["Linear Equations", "Fields", "system of linear equations, and its solution sets", "elementary row operations and echelon forms", "matrix operations", "invertible matrices"]}, {"unitName": "Module 2", "topics": ["Vector Spaces", "Vector spaces", "subspaces", "bases and dimension", "coordinates", "summary of row - equivalence", "computations concerning subspaces"]}, {"unitName": "Module 3", "topics": ["Symmetric Matrices and Quadratic Forms", "Diagonalization", "quadratic forms", "constrained optimization", "Singular value decomposition"]}]}]}